{
    "boxShadow": "none",
    "widgetName": "Buttons_Container1",
    "borderColor": "transparent",
    "isCanvas": true,
    "dynamicPropertyPathList": [{"key": "borderRadius"}],
    "displayName": "Container",
    "iconSVG": "/static/media/icon.1977dca3.svg",
    "topRow": 35,
    "bottomRow": 41,
    "parentRowSpace": 10,
    "type": "CONTAINER_WIDGET",
    "hideCard": false,
    "animateLoading": false,
    "parentColumnSpace": 11.09375,
    "dynamicTriggerPathList": [],
    "leftColumn": 42,
    "dynamicBindingPathList": [],
    "children": [{
        "boxShadow": "none",
        "widgetName": "Canvas3",
        "displayName": "Canvas",
        "topRow": 0,
        "bottomRow": 60,
        "parentRowSpace": 1,
        "type": "CANVAS_WIDGET",
        "canExtend": false,
        "hideCard": true,
        "minHeight": 400,
        "parentColumnSpace": 1,
        "leftColumn": 0,
        "dynamicBindingPathList": [],
        "key": "4n2qvrfenm",
        "labelTextSize": "0.875rem",
        "rightColumn": 266.25,
        "detachFromLayout": true,
        "widgetId": "3hd0p4ws70",
        "containerStyle": "none",
        "isVisible": true,
        "version": 1,
        "parentId": "iehhryz27k",
        "renderMode": "CANVAS",
        "isLoading": false,
        "borderRadius": "0px"
    }],
    "borderWidth": "0",
    "key": "uo2o06qxc4",
    "labelTextSize": "0.875rem",
    "backgroundColor": "#FFFFFF",
    "rightColumn": 64,
    "dynamicHeight": "FIXED",
    "widgetId": "iehhryz27k",
    "containerStyle": "card",
    "isVisible": true,
    "version": 1,
    "parentId": "ibrm8yci4n",
    "renderMode": "CANVAS",
    "isLoading": false,
    "borderRadius": "0px",
    "maxDynamicHeight": 9000,
    "minDynamicHeight": 4
}